tikcity/__init__.py
tikcity/core.py
tikcity-0.0.1.dist-info/METADATA
tikcity-0.0.1.dist-info/WHEEL
tikcity-0.0.1.dist-info/licenses/LICENSE
tikcity-0.0.1.dist-info/RECORD
