Metadata-Version: 2.4
Name: tikcity
Version: 0.0.1
Summary: Get the current time of any city in the world.
Project-URL: Homepage, https://github.com/mohankumar-mg/tikcity
Author: Mohankumar M G
License-File: LICENSE
Classifier: License :: OSI Approved :: MIT License
Classifier: Operating System :: OS Independent
Classifier: Programming Language :: Python :: 3
Requires-Python: >=3.7
Requires-Dist: geopy
Requires-Dist: pytz
Requires-Dist: timezonefinder
